perimeter/__init__.py
perimeter/admin.py
perimeter/apps.py
perimeter/forms.py
perimeter/management/__init__.py
perimeter/management/commands/__init__.py
perimeter/management/commands/create_access_token.py
perimeter/management/commands/list_access_tokens.py
perimeter/middleware.py
perimeter/migrations/0001_initial.py
perimeter/migrations/0002_auto_20150611_1234.py
perimeter/migrations/0003_auto_20150612_0151.py
perimeter/migrations/0004_auto_20170407_0639.py
perimeter/migrations/0005_auto_20180520_1037.py
perimeter/migrations/__init__.py
perimeter/models.py
perimeter/settings.py
perimeter/templates/perimeter/gateway.html
perimeter/urls.py
perimeter/views.py
django_perimeter-0.18.0.dist-info/METADATA
django_perimeter-0.18.0.dist-info/WHEEL
django_perimeter-0.18.0.dist-info/licenses/LICENSE
django_perimeter-0.18.0.dist-info/RECORD
